userlist/__init__.py
userlist/client.py
userlist/config.py
userlist/encoder.py
userlist/push.py
userlist/relation.py
userlist/resource.py
userlist/resources/__init__.py
userlist/resources/company.py
userlist/resources/event.py
userlist/resources/message.py
userlist/resources/relationship.py
userlist/resources/user.py
userlist_python-1.0.0.dist-info/LICENSE.txt
userlist_python-1.0.0.dist-info/METADATA
userlist_python-1.0.0.dist-info/WHEEL
userlist_python-1.0.0.dist-info/RECORD
