Metadata-Version: 2.3
Name: userlist-python
Version: 1.0.0
Summary: Python client for the Userlist API
Author: Benedikt Deicke
Author-email: benedikt@userlist.com
Requires-Python: >=3.8
Classifier: License :: OSI Approved :: MIT License
Classifier: Operating System :: OS Independent
Classifier: Programming Language :: Python :: 3
Classifier: Programming Language :: Python :: 3.8
Classifier: Programming Language :: Python :: 3.9
Classifier: Programming Language :: Python :: 3.10
Classifier: Programming Language :: Python :: 3.11
Classifier: Programming Language :: Python :: 3.12
Classifier: Programming Language :: Python :: 3.13
Requires-Dist: requests (>=2.31.0)
Project-URL: Homepage, https://github.com/userlist/userlist-python
Project-URL: Repository, https://github.com/userlist/userlist-python
